MANIFEST.in
setup.cfg
setup.py
bin/qless-py-worker
qless/__init__.py
qless/config.py
qless/exceptions.py
qless/job.py
qless/listener.py
qless/profile.py
qless/queue.py
qless/util.py
qless/qless-core/api.lua
qless/qless-core/base.lua
qless/qless-core/config.lua
qless/qless-core/job.lua
qless/qless-core/qless-lib.lua
qless/qless-core/qless.lua
qless/qless-core/queue.lua
qless/qless-core/recurring.lua
qless/qless-core/worker.lua
qless/workers/__init__.py
qless/workers/forking.py
qless/workers/greenlet.py
qless/workers/serial.py
qless_py.egg-info/PKG-INFO
qless_py.egg-info/SOURCES.txt
qless_py.egg-info/dependency_links.txt
qless_py.egg-info/requires.txt
qless_py.egg-info/top_level.txt
test/test_client.py
test/test_config.py
test/test_events.py
test/test_forking.py
test/test_greenlet.py
test/test_job.py
test/test_queue.py
test/test_serial.py
test/test_worker.py