Metadata-Version: 1.1
Name: qless-py
Version: 0.11.4
Summary: Redis-based Queue Management
Home-page: http://github.com/seomoz/qless-py
Author: Dan Lecocq
Author-email: dan@moz.com
License: MIT License
Keywords: redis,qless,job
Platform: UNKNOWN
Classifier: License :: OSI Approved :: MIT License
Classifier: Programming Language :: Python :: 2
Classifier: Programming Language :: Python :: 2.7
Classifier: Programming Language :: Python :: 3
Classifier: Programming Language :: Python :: 3.3
Classifier: Programming Language :: Python :: 3.4
Classifier: Programming Language :: Python :: 3.5
Classifier: Intended Audience :: Developers
Classifier: Operating System :: OS Independent
